setup.py
dopplr/__init__.py
dopplr/basequery.py
dopplr.egg-info/PKG-INFO
dopplr.egg-info/SOURCES.txt
dopplr.egg-info/dependency_links.txt
dopplr.egg-info/requires.txt
dopplr.egg-info/top_level.txt
dopplr/solr/__init__.py
dopplr/solr/client.py
dopplr/solr/querybuilder.py
dopplr/solr/responsemapper.py
dopplr/solr/query/__init__.py
dopplr/solr/query/boostquery.py
dopplr/solr/query/dismax.py
dopplr/solr/query/facets.py
dopplr/solr/query/grouping.py
dopplr/solr/query/highlighting.py
dopplr/solr/query/join.py
dopplr/solr/query/mlt.py
dopplr/solr/query/paging.py
dopplr/solr/query/query.py
dopplr/solr/query/spatial.py
dopplr/solr/query/spellcheck.py