Metadata-Version: 1.0
Name: dopplr
Version: 0.9.0-beta1
Summary: Dopplr is a Tornado based client library for Solr and ElasticSearch
Home-page: http://truemped.github.com/dopplr
Author: Daniel Truemper
Author-email: truemped@googlemail.com
License: UNKNOWN
Platform: UNKNOWN
